geoserverx/__init__.py
geoserverx/_async/__init__.py
geoserverx/_async/gsx.py
geoserverx/_sync/__init__.py
geoserverx/_sync/gsx.py
geoserverx/cli/cli.py
geoserverx/models/__init__.py
geoserverx/models/coverages_layer.py
geoserverx/models/coverages_store.py
geoserverx/models/data_store.py
geoserverx/models/featuretypes_layer.py
geoserverx/models/geofence.py
geoserverx/models/gs_response.py
geoserverx/models/layer_group.py
geoserverx/models/layers.py
geoserverx/models/style.py
geoserverx/models/workspace.py
geoserverx/utils/__init__.py
geoserverx/utils/auth.py
geoserverx/utils/custom_exceptions.py
geoserverx/utils/enums.py
geoserverx/utils/errors.py
geoserverx/utils/http_client.py
geoserverx/utils/logger.py
geoserverx/utils/services/async_datastore.py
geoserverx/utils/services/datastore.py
geoserverx-0.0.4.dist-info/LICENSE
geoserverx-0.0.4.dist-info/METADATA
geoserverx-0.0.4.dist-info/WHEEL
geoserverx-0.0.4.dist-info/entry_points.txt
geoserverx-0.0.4.dist-info/RECORD
