Metadata-Version: 2.1
Name: geoserverx
Version: 0.0.4
Summary: geoserverx is a modern python and CLI package for communicating with Geoserver.
Author: krishnaglodha
Author-email: krishnaglodha@gmail.com
Requires-Python: >=3.9,<4.0
Classifier: Programming Language :: Python :: 3
Classifier: Programming Language :: Python :: 3.9
Classifier: Programming Language :: Python :: 3.10
Classifier: Programming Language :: Python :: 3.11
Classifier: Programming Language :: Python :: 3.12
Classifier: Programming Language :: Python :: 3.13
Requires-Dist: httpx (>=0.24.1,<0.25.0)
Requires-Dist: pydantic (==2.8.2)
Requires-Dist: rich (>=12.5.1,<13.0.0)
Requires-Dist: typer (>=0.4.1,<0.5.0)
